[{"originX":"left","originY":"top","width":100,"height":100,"scaleX":1,"scaleY":1,"type":0,"gradAngle":0,"gradRatio":0,"animation":0,"videoStartTime":0,"videoEndTime":0,"adjustment":{"vibrance":1,"blur":0,"black_point":1,"brightness":1,"brilliance":1,"contrast":1,"exposure":1,"highlight":1,"saturation":1,"shadow":1,"sharpness":1,"tint":1},"opacity":100,"filter":{"intensity":1,"type":0},"crop":{"top":0,"bottom":0,"left":0,"right":0},"flip":{"h":false,"v":false},"layers":[{"width":41.776318,"height":26.666666,"scaleX":1,"scaleY":1,"rotation":-0,"opacity":100,"type":0,"resizeType":0,"lockType":0,"animation":0,"adjustment":{"vibrance":1,"blur":0,"black_point":1,"brightness":1,"brilliance":1,"contrast":1,"exposure":1,"highlight":1,"saturation":1,"shadow":1,"sharpness":1,"tint":1},"filter":{"intensity":1,"type":0},"crop":{"top":0,"bottom":0,"left":0,"right":0},"flip":{"h":false,"v":false},"videoStartTime":0,"videoEndTime":0,"size":0,"a":0,"isEditable":0,"layerType":1,"isUrl":0,"isVideo":false,"editableTitle":"null","image":"uploadedFiles\/sticker_file\/45fcb657c25861266baac0e757d7245d2adede3a1733201864.png","curve":0,"format":{"alignment":0,"alignPos":0,"bold":false,"italic":false,"capital":false,"underline":false,"bulletSpan":false,"numericSpan":false},"left":79.07407,"spacing":{"anchor":0,"letter":0,"line":0,"lineMultiplier":0},"top":-7.5520835,"effectType":0,"link":"","update":true,"originX":"left","originY":"top"},{"width":43.092106,"height":26.11111,"scaleX":1,"scaleY":1,"rotation":-0,"opacity":100,"type":0,"resizeType":0,"lockType":0,"animation":0,"adjustment":{"vibrance":1,"blur":0,"black_point":1,"brightness":1,"brilliance":1,"contrast":1,"exposure":1,"highlight":1,"saturation":1,"shadow":1,"sharpness":1,"tint":1},"filter":{"intensity":1,"type":0},"crop":{"top":0,"bottom":0,"left":0,"right":0},"flip":{"h":false,"v":false},"videoStartTime":0,"videoEndTime":0,"size":0,"a":0,"isEditable":0,"layerType":1,"isUrl":0,"isVideo":false,"editableTitle":"null","image":"uploadedFiles\/sticker_file\/3465252ebc2a74f5d5c93bf99150c7d78bbddb911733201864.png","curve":0,"format":{"alignment":0,"alignPos":0,"bold":false,"italic":false,"capital":false,"underline":false,"bulletSpan":false,"numericSpan":false},"left":-25.092592,"spacing":{"anchor":0,"letter":0,"line":0,"lineMultiplier":0},"top":-9.947917,"effectType":0,"link":"","update":true,"originX":"left","originY":"top"},{"width":96.54605,"height":26.944445,"scaleX":1,"scaleY":1,"rotation":-0,"opacity":100,"type":0,"resizeType":0,"lockType":0,"animation":0,"adjustment":{"vibrance":1,"blur":0,"black_point":1,"brightness":1,"brilliance":1,"contrast":1,"exposure":1,"highlight":1,"saturation":1,"shadow":1,"sharpness":1,"tint":1},"filter":{"intensity":1,"type":0},"crop":{"top":0,"bottom":0,"left":0,"right":0},"flip":{"h":false,"v":false},"videoStartTime":0,"videoEndTime":0,"size":0,"a":0,"isEditable":0,"layerType":1,"isUrl":0,"isVideo":false,"editableTitle":"null","image":"uploadedFiles\/sticker_file\/74c497a35a50e383adf5904939303d95cd2afc691733201864.png","curve":0,"format":{"alignment":0,"alignPos":0,"bold":false,"italic":false,"capital":false,"underline":false,"bulletSpan":false,"numericSpan":false},"left":3.4259257,"spacing":{"anchor":0,"letter":0,"line":0,"lineMultiplier":0},"top":73.4375,"effectType":0,"link":"","update":true,"originX":"left","originY":"top"},{"width":79.11184,"height":30.74074,"scaleX":1,"scaleY":1,"rotation":-0,"opacity":100,"type":0,"resizeType":0,"lockType":0,"animation":0,"adjustment":{"vibrance":1,"blur":0,"black_point":1,"brightness":1,"brilliance":1,"contrast":1,"exposure":1,"highlight":1,"saturation":1,"shadow":1,"sharpness":1,"tint":1},"filter":{"intensity":1,"type":0},"crop":{"top":0,"bottom":0,"left":0,"right":0},"flip":{"h":false,"v":false},"videoStartTime":0,"videoEndTime":0,"size":0,"a":0,"isEditable":0,"layerType":1,"isUrl":0,"isVideo":false,"editableTitle":"null","image":"uploadedFiles\/sticker_file\/59d7d8e6848cf50845088a81c7b2f5c0b7d2e0181733201864.png","curve":0,"format":{"alignment":0,"alignPos":0,"bold":false,"italic":false,"capital":false,"underline":false,"bulletSpan":false,"numericSpan":false},"left":10.444077,"spacing":{"anchor":0,"letter":0,"line":0,"lineMultiplier":0},"top":69.6875,"effectType":0,"link":"","update":true,"originX":"left","originY":"top"},{"width":14.473684,"height":35.27778,"scaleX":1,"scaleY":1,"rotation":-0,"opacity":100,"type":0,"resizeType":0,"lockType":0,"animation":0,"adjustment":{"vibrance":1,"blur":0,"black_point":1,"brightness":1,"brilliance":1,"contrast":1,"exposure":1,"highlight":1,"saturation":1,"shadow":1,"sharpness":1,"tint":1},"filter":{"intensity":1,"type":0},"crop":{"top":0,"bottom":0,"left":0,"right":0},"flip":{"h":false,"v":false},"videoStartTime":0,"videoEndTime":0,"size":0,"a":0,"isEditable":0,"layerType":1,"isUrl":0,"isVideo":false,"editableTitle":"null","image":"uploadedFiles\/sticker_file\/b89d70789181f380ec6870cc250d422e1eda42cc1733201864.png","curve":0,"format":{"alignment":0,"alignPos":0,"bold":false,"italic":false,"capital":false,"underline":false,"bulletSpan":false,"numericSpan":false},"left":14.074073,"spacing":{"anchor":0,"letter":0,"line":0,"lineMultiplier":0},"top":65.15625,"effectType":0,"link":"","update":true,"originX":"left","originY":"top"},{"width":39.80263,"height":12.777778,"scaleX":1,"scaleY":1,"rotation":-0,"opacity":100,"type":0,"color":"#FCF2E4","resizeType":0,"lockType":0,"animation":0,"adjustment":{"vibrance":0,"blur":0,"black_point":0,"brightness":0,"brilliance":0,"contrast":0,"exposure":0,"highlight":0,"saturation":0,"shadow":0,"sharpness":0,"tint":0},"filter":{"intensity":0,"type":0},"crop":{"top":0,"bottom":0,"left":0,"right":0},"flip":{"h":false,"v":false},"videoStartTime":0,"videoEndTime":0,"text":"LUNCH \r\nInvitation","font":"AbhayaLibre-SemiBold.ttf","size":58.5092,"a":0,"isEditable":0,"layerType":2,"isUrl":0,"isVideo":false,"editableTitle":"null","curve":0,"format":{"alignment":4,"alignPos":1,"c":"ALIGN_CENTER","textAlign":"center","bold":true,"italic":false,"capital":false,"underline":false,"bulletSpan":false,"numericSpan":false},"left":30.098688,"spacing":{"anchor":1,"letter":0,"line":0,"lineMultiplier":1},"top":7.174587,"effectType":0,"link":"","update":false,"originX":"left","originY":"top"},{"width":73.51974,"height":4.9074073,"scaleX":1,"scaleY":1,"rotation":-0,"opacity":100,"type":0,"color":"#FCF2E4","resizeType":0,"lockType":0,"animation":0,"adjustment":{"vibrance":0,"blur":0,"black_point":0,"brightness":0,"brilliance":0,"contrast":0,"exposure":0,"highlight":0,"saturation":0,"shadow":0,"sharpness":0,"tint":0},"filter":{"intensity":0,"type":0},"crop":{"top":0,"bottom":0,"left":0,"right":0},"flip":{"h":false,"v":false},"videoStartTime":0,"videoEndTime":0,"text":"A taste of togetherness at noon!","font":"GreatVibes-Regular.ttf","size":41.875,"a":0,"isEditable":0,"layerType":2,"isUrl":0,"isVideo":false,"editableTitle":"null","curve":0,"format":{"alignment":4,"alignPos":1,"c":"ALIGN_CENTER","textAlign":"center","bold":true,"italic":false,"capital":false,"underline":false,"bulletSpan":false,"numericSpan":false},"left":13.240136,"spacing":{"anchor":1,"letter":0,"line":0,"lineMultiplier":1},"top":24.493845,"effectType":0,"link":"","update":false,"originX":"left","originY":"top"},{"width":15.953947,"height":5.0925927,"scaleX":1,"scaleY":1,"rotation":-0,"opacity":100,"type":0,"color":"#FCF2E4","resizeType":0,"lockType":0,"animation":0,"adjustment":{"vibrance":0,"blur":0,"black_point":0,"brightness":0,"brilliance":0,"contrast":0,"exposure":0,"highlight":0,"saturation":0,"shadow":0,"sharpness":0,"tint":0},"filter":{"intensity":0,"type":0},"crop":{"top":0,"bottom":0,"left":0,"right":0},"flip":{"h":false,"v":false},"videoStartTime":0,"videoEndTime":0,"text":"Venue","font":"GreatVibes-Regular.ttf","size":43.875,"a":0,"isEditable":0,"layerType":2,"isUrl":0,"isVideo":false,"editableTitle":"null","curve":0,"format":{"alignment":4,"alignPos":1,"c":"ALIGN_CENTER","textAlign":"center","bold":true,"italic":false,"capital":false,"underline":false,"bulletSpan":false,"numericSpan":false},"left":42.023026,"spacing":{"anchor":1,"letter":0,"line":0,"lineMultiplier":1},"top":49.235558,"effectType":0,"link":"","update":false,"originX":"left","originY":"top"},{"width":61.019737,"height":6.111111,"scaleX":1,"scaleY":1,"rotation":-0,"opacity":100,"type":0,"color":"#FCF2E4","resizeType":0,"lockType":0,"animation":0,"adjustment":{"vibrance":0,"blur":0,"black_point":0,"brightness":0,"brilliance":0,"contrast":0,"exposure":0,"highlight":0,"saturation":0,"shadow":0,"sharpness":0,"tint":0},"filter":{"intensity":0,"type":0},"crop":{"top":0,"bottom":0,"left":0,"right":0},"flip":{"h":false,"v":false},"videoStartTime":0,"videoEndTime":0,"text":"THE ROYALE CHULAN KUALA LUMPUR \r\nTAMING SARI III BALLROOM S JALAN CONLAY \r\n50450 KUALA LUMPUR MALAYSIA","font":"AbhayaLibre-SemiBold.ttf","size":18.5,"a":0,"isEditable":0,"layerType":2,"isUrl":0,"isVideo":false,"editableTitle":"null","curve":0,"format":{"alignment":4,"alignPos":1,"c":"ALIGN_CENTER","textAlign":"center","bold":true,"italic":false,"capital":false,"underline":false,"bulletSpan":false,"numericSpan":false},"left":19.490131,"spacing":{"anchor":1,"letter":0,"line":0,"lineMultiplier":1},"top":55.538113,"effectType":0,"link":"","update":false,"originX":"left","originY":"top"},{"width":41.44737,"height":3.3333333,"scaleX":1,"scaleY":1,"rotation":-0,"opacity":100,"type":0,"color":"#FCF2E4","resizeType":0,"lockType":0,"animation":0,"adjustment":{"vibrance":0,"blur":0,"black_point":0,"brightness":0,"brilliance":0,"contrast":0,"exposure":0,"highlight":0,"saturation":0,"shadow":0,"sharpness":0,"tint":0},"filter":{"intensity":0,"type":0},"crop":{"top":0,"bottom":0,"left":0,"right":0},"flip":{"h":false,"v":false},"videoStartTime":0,"videoEndTime":0,"text":"25 January 2025","font":"News706BT.ttf","size":29.875,"a":0,"isEditable":0,"layerType":2,"isUrl":0,"isVideo":false,"editableTitle":"null","curve":0,"format":{"alignment":4,"alignPos":1,"c":"ALIGN_CENTER","textAlign":"center","bold":true,"italic":false,"capital":false,"underline":false,"bulletSpan":false,"numericSpan":false},"left":29.276312,"spacing":{"anchor":1,"letter":0,"line":0,"lineMultiplier":1},"top":32.712357,"effectType":0,"link":"","update":false,"originX":"left","originY":"top"},{"width":47.69737,"height":3.3333333,"scaleX":1,"scaleY":1,"rotation":-0,"opacity":100,"type":0,"color":"#FCF2E4","resizeType":0,"lockType":0,"animation":0,"adjustment":{"vibrance":0,"blur":0,"black_point":0,"brightness":0,"brilliance":0,"contrast":0,"exposure":0,"highlight":0,"saturation":0,"shadow":0,"sharpness":0,"tint":0},"filter":{"intensity":0,"type":0},"crop":{"top":0,"bottom":0,"left":0,"right":0},"flip":{"h":false,"v":false},"videoStartTime":0,"videoEndTime":0,"text":"11:30 AM - 1:00PM","font":"News706BT.ttf","size":29.875,"a":0,"isEditable":0,"layerType":2,"isUrl":0,"isVideo":false,"editableTitle":"null","curve":0,"format":{"alignment":4,"alignPos":1,"c":"ALIGN_CENTER","textAlign":"center","bold":true,"italic":false,"capital":false,"underline":false,"bulletSpan":false,"numericSpan":false},"left":26.151312,"spacing":{"anchor":1,"letter":0,"line":0,"lineMultiplier":1},"top":39.587357,"effectType":0,"link":"","update":false,"originX":"left","originY":"top"}],"a":0,"fromDraft":false,"layerType":0,"autoCreate":false,"thumb":"uploadedFiles\/thumb_file\/cf5b21deef676281db47a2073e727aa63a1673821733201864.jpg","image":"uploadedFiles\/bg_file\/1a0d9dbfb908aef78f69bbe7c27360a7d60303ee1733201864.jpg","color":"#ffffff","left":0,"top":0}]